bact_analysis/__init__.py
bact_analysis/bba/__init__.py
bact_analysis/bba/calc.py
bact_analysis/transverse/__init__.py
bact_analysis/transverse/calc.py
bact_analysis/transverse/distorted_orbit.py
bact_analysis/transverse/process.py
bact_analysis/transverse/twiss_interpolate.py
bact_analysis/utils/__init__.py
bact_analysis/utils/preprocess.py
bact_analysis-0.1.0.dist-info/LICENSE
bact_analysis-0.1.0.dist-info/METADATA
bact_analysis-0.1.0.dist-info/WHEEL
bact_analysis-0.1.0.dist-info/RECORD
